hermes_framing_nodes/__init__.py
hermes_framing_nodes/burst_node.py
hermes_framing_nodes-1.0.2.dist-info/METADATA
hermes_framing_nodes-1.0.2.dist-info/WHEEL
hermes_framing_nodes-1.0.2.dist-info/RECORD
