Metadata-Version: 2.4
Name: hermes-framing-nodes
Version: 1.0.2
Summary: Hermes framing nodes translating between streams and frames
Author-email: floris vernieuwe <floris@vernieuwe.eu>
Requires-Python: >=3.10
Requires-Dist: burst-link-protocol>=1.1.5
Requires-Dist: hermes-stream-nodes>=1.0.1
Requires-Dist: node-hermes-core>=1.2.0
